{
    "homepage": "https://minecraft.curseforge.com/projects/commander",
    "1.10.2": {
        "1.0.1": "Second update of Commander mod. This update now makes Commander mod depend upon McLib (version 1.0.2) mod, and also adds multiple commands in line parsing.",
        "1.0": "Initial release of Commander adds very basic features."
    },
    "1.11.2": {
        "1.0.1": "Second update of Commander mod. This update now makes Commander mod depend upon McLib (version 1.0.2) mod, and also adds multiple commands in line parsing.",
        "1.0": "Initial release of Commander adds very basic features."
    },
    "1.12.2": {
        "1.0.1": "Second update of Commander mod. This update now makes Commander mod depend upon McLib (version 1.0.2) mod, and also adds multiple commands in line parsing.",
        "1.0": "Initial release of Commander adds very basic features."
    },
    "promos": {
        "1.10.2-latest": "1.0.1",
        "1.10.2-recommended": "1.0.1",
        "1.11.2-latest": "1.0.1",
        "1.11.2-recommended": "1.0.1",
        "1.12.2-latest": "1.0.1",
        "1.12.2-recommended": "1.0.1"
    }
}